gingko/__init__.py
gingko/core.py
gingko/dataframes.py
gingko/utils.py
gingko/wikiscraper.py
gingko-0.1.1.dist-info/METADATA
gingko-0.1.1.dist-info/WHEEL
gingko-0.1.1.dist-info/top_level.txt
gingko-0.1.1.dist-info/RECORD
