Metadata-Version: 2.1
Name: gingko
Version: 0.1.1
Summary: UNKNOWN
Home-page: UNKNOWN
Author: UNKNOWN
Author-email: UNKNOWN
License: UNKNOWN
Platform: UNKNOWN
Requires-Dist: dataclasses
Requires-Dist: numpy
Requires-Dist: pandas
Requires-Dist: auto-mix-prep
Requires-Dist: beautifulsoup4
